{
    "Ar36": {
        "error": 4.586215028078756e-07,
        "error_type": "SEM",
        "filter_outliers_dict": {
            "filter_outliers": true,
            "iterations": 1,
            "std_devs": 2,
            "use_iqr_filtering": false,
            "use_standard_deviation_filtering": true
        },
        "fit": "linear",
        "fn": 71,
        "include_baseline_error": false,
        "n": 71,
        "outlier_excluded": [],
        "reviewed": true,
        "user_excluded": [],
        "value": 9.013130679970323e-05
    },
    "Ar36L4": {
        "error": 1.7948963164696552e-07,
        "error_type": "SEM",
        "filter_outliers_dict": {
            "filter_outliers": true,
            "iterations": 1,
            "std_devs": 2,
            "use_iqr_filtering": false,
            "use_standard_deviation_filtering": true
        },
        "fit": "parabolic",
        "fn": 420,
        "include_baseline_error": false,
        "n": 420,
        "outlier_excluded": [],
        "reviewed": true,
        "user_excluded": [],
        "value": 9.515695501234845e-05
    },
    "Ar37": {
        "error": 5.542843780701256e-07,
        "error_type": "SEM",
        "filter_outliers_dict": {
            "filter_outliers": true,
            "iterations": 1,
            "std_devs": 2
        },
        "fit": "linear",
        "value": -9.501066259475069e-06
    },
    "Ar37L2": {
        "error": 2.2614728293957867e-07,
        "error_type": "SEM",
        "filter_outliers_dict": {
            "filter_outliers": true,
            "iterations": 1,
            "std_devs": 2
        },
        "fit": "linear",
        "value": -9.343322611936284e-06
    },
    "Ar38": {
        "error": 1.754872926661561e-07,
        "error_type": "SEM",
        "filter_outliers_dict": {
            "filter_outliers": true,
            "iterations": 1,
            "std_devs": 2
        },
        "fit": "linear",
        "value": 4.175488951444128e-06
    },
    "Ar38Ax": {
        "error": 2.530391985036796e-07,
        "error_type": "SEM",
        "filter_outliers_dict": {
            "filter_outliers": true,
            "iterations": 1,
            "std_devs": 2
        },
        "fit": "linear",
        "value": 8.23399079300767e-06
    },
    "Ar39": {
        "error": 4.761111346739221e-07,
        "error_type": "SEM",
        "filter_outliers_dict": {
            "filter_outliers": true,
            "iterations": 1,
            "std_devs": 2
        },
        "fit": "linear",
        "value": -9.101713167901492e-07
    },
    "Ar39H2": {
        "error": 7.243251635316774e-07,
        "error_type": "SEM",
        "filter_outliers_dict": {
            "filter_outliers": true,
            "iterations": 1,
            "std_devs": 2
        },
        "fit": "linear",
        "value": 2.2445630668117853e-07
    },
    "Ar40": {
        "error": 1.0514402800425855e-05,
        "error_type": "SEM",
        "filter_outliers_dict": {
            "filter_outliers": true,
            "iterations": 1,
            "std_devs": 2,
            "use_iqr_filtering": false,
            "use_standard_deviation_filtering": true
        },
        "fit": "parabolic",
        "fn": 71,
        "include_baseline_error": false,
        "n": 71,
        "outlier_excluded": [],
        "reviewed": true,
        "user_excluded": [],
        "value": 0.027774292861601588
    },
    "Ar40H4": {
        "error": 1.666982903777393e-05,
        "error_type": "SEM",
        "filter_outliers_dict": {
            "filter_outliers": true,
            "iterations": 1,
            "std_devs": 2,
            "use_iqr_filtering": false,
            "use_standard_deviation_filtering": true
        },
        "fit": "parabolic",
        "fn": 36,
        "include_baseline_error": false,
        "n": 36,
        "outlier_excluded": [],
        "reviewed": true,
        "user_excluded": [],
        "value": 0.027473308743134698
    }
}