{
    "Ar36": {
        "error": 1.5874455458451097e-07,
        "error_type": "SEM",
        "filter_outliers_dict": {
            "filter_outliers": true,
            "iterations": 1,
            "std_devs": 2,
            "use_iqr_filtering": false,
            "use_standard_deviation_filtering": true
        },
        "fit": "linear",
        "fn": 36,
        "include_baseline_error": false,
        "n": 36,
        "outlier_excluded": [],
        "reviewed": true,
        "user_excluded": [],
        "value": 3.7603866677716623e-06
    },
    "Ar36L4": {
        "error": 2.023200896697825e-08,
        "error_type": "SEM",
        "filter_outliers_dict": {
            "filter_outliers": true,
            "iterations": 1,
            "std_devs": 2,
            "use_iqr_filtering": false,
            "use_standard_deviation_filtering": true
        },
        "fit": "linear",
        "fn": 540,
        "include_baseline_error": false,
        "n": 540,
        "outlier_excluded": [],
        "reviewed": true,
        "user_excluded": [],
        "value": 1.2723233350610805e-06
    },
    "Ar37": {
        "error": 1.6398165730968763e-07,
        "error_type": "SEM",
        "filter_outliers_dict": {
            "filter_outliers": true,
            "iterations": 1,
            "std_devs": 2
        },
        "fit": "linear",
        "value": -8.846135912322944e-06
    },
    "Ar37L2": {
        "error": 1.1813799119364024e-07,
        "error_type": "SEM",
        "filter_outliers_dict": {
            "filter_outliers": true,
            "iterations": 1,
            "std_devs": 2
        },
        "fit": "linear",
        "value": -9.581825043541412e-06
    },
    "Ar38": {
        "error": 1.2769834507502826e-07,
        "error_type": "SEM",
        "filter_outliers_dict": {
            "filter_outliers": true,
            "iterations": 1,
            "std_devs": 2
        },
        "fit": "linear",
        "value": -1.222345022097098e-05
    },
    "Ar38Ax": {
        "error": 2.207258213622492e-07,
        "error_type": "SEM",
        "filter_outliers_dict": {
            "filter_outliers": true,
            "iterations": 1,
            "std_devs": 2
        },
        "fit": "linear",
        "value": -7.97456821822294e-06
    },
    "Ar39": {
        "error": 2.0463138702139965e-07,
        "error_type": "SEM",
        "filter_outliers_dict": {
            "filter_outliers": true,
            "iterations": 1,
            "std_devs": 2
        },
        "fit": "linear",
        "value": -4.043415326791243e-06
    },
    "Ar39H2": {
        "error": 2.372750314355887e-07,
        "error_type": "SEM",
        "filter_outliers_dict": {
            "filter_outliers": true,
            "iterations": 1,
            "std_devs": 2
        },
        "fit": "linear",
        "value": -2.9756361977505e-06
    },
    "Ar40": {
        "error": 1.7898779499337123e-06,
        "error_type": "SEM",
        "filter_outliers_dict": {
            "filter_outliers": true,
            "iterations": 1,
            "std_devs": 2,
            "use_iqr_filtering": false,
            "use_standard_deviation_filtering": true
        },
        "fit": "parabolic",
        "fn": 36,
        "include_baseline_error": false,
        "n": 36,
        "outlier_excluded": [],
        "reviewed": true,
        "user_excluded": [],
        "value": 0.00026386188935006657
    },
    "Ar40H4": {
        "error": 2.117412848780952e-06,
        "error_type": "SEM",
        "filter_outliers_dict": {
            "filter_outliers": true,
            "iterations": 1,
            "std_devs": 2,
            "use_iqr_filtering": false,
            "use_standard_deviation_filtering": true
        },
        "fit": "parabolic",
        "fn": 24,
        "include_baseline_error": false,
        "n": 24,
        "outlier_excluded": [],
        "reviewed": true,
        "user_excluded": [],
        "value": 0.0002686209059712671
    }
}