{
    "Ar36": {
        "error": 1.415975717119157e-07,
        "error_type": "",
        "fit": "previous",
        "references": [
            {
                "exclude": false,
                "record_id": "ba-01-N-3378"
            }
        ],
        "value": 4.726140568914087e-07
    },
    "Ar37": {
        "error": 1.1052386632889132e-07,
        "error_type": "",
        "fit": "previous",
        "references": [
            {
                "exclude": false,
                "record_id": "ba-01-N-3378"
            }
        ],
        "value": -3.7059015342590813e-07
    },
    "Ar38": {
        "error": 1.730434906849859e-07,
        "error_type": "",
        "fit": "previous",
        "references": [
            {
                "exclude": false,
                "record_id": "ba-01-N-3378"
            }
        ],
        "value": 2.934425906383013e-07
    },
    "Ar39": {
        "error": 1.9282449267182507e-07,
        "error_type": "",
        "fit": "previous",
        "references": [
            {
                "exclude": false,
                "record_id": "ba-01-N-3378"
            }
        ],
        "value": 1.7606400301029885e-06
    },
    "Ar40": {
        "error": 2.394296024639335e-06,
        "error_type": "",
        "fit": "previous",
        "references": [
            {
                "exclude": false,
                "record_id": "ba-01-N-3378"
            }
        ],
        "value": 0.00011846433592329432
    }
}