{
    "Ar36": {
        "error": 1.3986619874594295e-07,
        "error_type": "",
        "fit": "previous",
        "references": [
            {
                "exclude": false,
                "record_id": "ba-01-n-3351"
            }
        ],
        "value": 3.03147944974098e-07
    },
    "Ar36L4": {
        "error": 1.3442787990037273e-08,
        "error_type": "",
        "fit": "previous",
        "references": [
            {
                "exclude": false,
                "record_id": "ba-01-n-3351"
            }
        ],
        "value": 6.405215573492188e-07
    },
    "Ar37": {
        "error": 2.837579882087189e-07,
        "error_type": "",
        "fit": "previous",
        "references": [
            {
                "exclude": false,
                "record_id": "ba-01-n-3351"
            }
        ],
        "value": -7.801707972829831e-07
    },
    "Ar37L2": {
        "error": 1.737030312166326e-07,
        "error_type": "",
        "fit": "previous",
        "references": [
            {
                "exclude": false,
                "record_id": "ba-01-n-3351"
            }
        ],
        "value": -3.3542833737998405e-07
    },
    "Ar38": {
        "error": 1.2988396626495244e-07,
        "error_type": "",
        "fit": "previous",
        "references": [
            {
                "exclude": false,
                "record_id": "ba-01-n-3351"
            }
        ],
        "value": -3.77964061510508e-07
    },
    "Ar38Ax": {
        "error": 2.1286223526518807e-07,
        "error_type": "",
        "fit": "previous",
        "references": [
            {
                "exclude": false,
                "record_id": "ba-01-n-3351"
            }
        ],
        "value": -8.698420746812564e-08
    },
    "Ar39": {
        "error": 1.690717333017463e-07,
        "error_type": "",
        "fit": "previous",
        "references": [
            {
                "exclude": false,
                "record_id": "ba-01-n-3351"
            }
        ],
        "value": 1.7430446063321397e-06
    },
    "Ar39H2": {
        "error": 1.3605797017661215e-07,
        "error_type": "",
        "fit": "previous",
        "references": [
            {
                "exclude": false,
                "record_id": "ba-01-n-3351"
            }
        ],
        "value": 6.754061512806596e-07
    },
    "Ar40": {
        "error": 1.4809293471930002e-06,
        "error_type": "",
        "fit": "previous",
        "references": [
            {
                "exclude": false,
                "record_id": "ba-01-n-3351"
            }
        ],
        "value": 0.00011793554784070691
    },
    "Ar40H4": {
        "error": 2.069138799727598e-06,
        "error_type": "",
        "fit": "previous",
        "references": [
            {
                "exclude": false,
                "record_id": "ba-01-n-3351"
            }
        ],
        "value": 0.00012135250721028947
    }
}